{
    "items": [
      {
        "concept": {
          "CONCEPT_ID": 37395717,
          "CONCEPT_NAME": "Depression screening using PHQ-9 (Patient Health Questionnaire 9) score",
          "STANDARD_CONCEPT": "S",
          "STANDARD_CONCEPT_CAPTION": "Standard",
          "INVALID_REASON": "V",
          "INVALID_REASON_CAPTION": "Valid",
          "CONCEPT_CODE": "715252007",
          "DOMAIN_ID": "Measurement",
          "VOCABULARY_ID": "SNOMED",
          "CONCEPT_CLASS_ID": "Procedure"
        },
        "isExcluded": false,
        "includeDescendants": true,
        "includeMapped": false
      },
      {
        "concept": {
          "CONCEPT_ID": 44804610,
          "CONCEPT_NAME": "PHQ-9 - Patient health questionnaire 9",
          "STANDARD_CONCEPT": "S",
          "STANDARD_CONCEPT_CAPTION": "Standard",
          "INVALID_REASON": "V",
          "INVALID_REASON_CAPTION": "Valid",
          "CONCEPT_CODE": "758711000000105",
          "DOMAIN_ID": "Measurement",
          "VOCABULARY_ID": "SNOMED",
          "CONCEPT_CLASS_ID": "Staging / Scales"
        },
        "isExcluded": false,
        "includeDescendants": true,
        "includeMapped": false
      }
    ]
  }